.coveragerc
ChangeLog
LICENSE
README.md
host.json
lifecycle-rules.json
requirements.txt
setup.cfg
setup.py
strategy.ini
.github/workflows/publish-pypi.yml
.github/workflows/unit-tests.yml
docs/deployment_view.pdf
docs/deployment_view.svg
docs/process_view.pdf
docs/process_view.svg
mag_archiver/__init__.py
mag_archiver/azure.py
mag_archiver/function.json
mag_archiver/mag.py
mag_archiver/mag_archiver.py
mag_archiver.egg-info/PKG-INFO
mag_archiver.egg-info/SOURCES.txt
mag_archiver.egg-info/dependency_links.txt
mag_archiver.egg-info/not-zip-safe
mag_archiver.egg-info/pbr.json
mag_archiver.egg-info/requires.txt
mag_archiver.egg-info/top_level.txt
tests/__init__.py
tests/test_azure.py
tests/test_mag.py