Metadata-Version: 2.1
Name: mag-archiver
Version: 2020.12.0
Summary: mag-archiver is an Azure service that automatically archives Microsoft Academic Graph (MAG) releases so that they can be transferred to other cloud services.
Home-page: https://github.com/The-Academic-Observatory/mag-archiver
Author: Curtin University
Author-email: agent@observatory.academy
License: Apache License Version 2.0
Project-URL: Bug Tracker, https://github.com/The-Academic-Observatory/mag-archiver/issues
Project-URL: Documentation, https://github.com/The-Academic-Observatory/mag-archiver
Project-URL: Source Code, https://github.com/The-Academic-Observatory/mag-archiver
Keywords: MAG,Microsoft Academic Graph,science,data,workflows,academic institutes
Platform: UNKNOWN
Classifier: Development Status :: 2 - Pre-Alpha
Classifier: Intended Audience :: Developers
Classifier: Intended Audience :: Science/Research
Classifier: Programming Language :: Python :: 3 :: Only
Classifier: Programming Language :: Python :: 3
Classifier: Programming Language :: Python :: 3.7
Classifier: Topic :: Scientific/Engineering
Classifier: Topic :: Software Development :: Libraries
Classifier: Topic :: Software Development :: Libraries :: Python Modules
Classifier: Topic :: Utilities
Requires-Python: >=3.6.6
Provides-Extra: tests
